package com.rongdu.cashloan.manage.controller;

import com.rongdu.cashloan.cl.service.ChannelThirdLogService;
import com.rongdu.cashloan.cl.service.ClBorrowService;
import com.rongdu.cashloan.cl.service.ClSmsService;
import com.rongdu.cashloan.cl.service.UserPhoneBlacklistService;
import com.rongdu.cashloan.core.common.web.controller.BaseController;
import com.rongdu.cashloan.manage.service.UserService;
import javax.annotation.Resource;
import org.springframework.context.annotation.Scope;
import org.springframework.stereotype.Controller;

@Controller
@Scope("prototype")
public class ChannelThridRegisterController
  extends BaseController
{
  @Resource
  private ClSmsService clSmsService;
  @Resource
  private UserPhoneBlacklistService userPhoneBlacklistService;
  @Resource
  private ClBorrowService clBorrowService;
  @Resource(name="clUserService_")
  private UserService userService;
  @Resource
  private ChannelThirdLogService channelThirdLogService;
  
  /* Error */
  @org.springframework.web.bind.annotation.RequestMapping(value={"/register/receive/phone.htm"}, method={org.springframework.web.bind.annotation.RequestMethod.GET, org.springframework.web.bind.annotation.RequestMethod.POST})
  public void compeletAuthReport(javax.servlet.http.HttpServletRequest request, @org.springframework.web.bind.annotation.RequestBody String data)
  {
    // Byte code:
    //   0: new 39	java/util/HashMap
    //   3: dup
    //   4: invokespecial 41	java/util/HashMap:<init>	()V
    //   7: astore_3
    //   8: aload_2
    //   9: invokestatic 42	org/springframework/util/StringUtils:isEmpty	(Ljava/lang/Object;)Z
    //   12: ifne +13 -> 25
    //   15: aload_2
    //   16: ldc 48
    //   18: invokestatic 50	com/rongdu/cashloan/core/common/util/JsonUtil:parse	(Ljava/lang/String;Ljava/lang/Class;)Ljava/lang/Object;
    //   21: checkcast 48	java/util/Map
    //   24: astore_3
    //   25: aload_3
    //   26: ldc 56
    //   28: invokeinterface 58 2 0
    //   33: checkcast 62	java/lang/String
    //   36: astore 4
    //   38: lconst_0
    //   39: lstore 5
    //   41: ldc 64
    //   43: astore 7
    //   45: new 39	java/util/HashMap
    //   48: dup
    //   49: invokespecial 41	java/util/HashMap:<init>	()V
    //   52: astore 8
    //   54: ldc 66
    //   56: aload_3
    //   57: ldc 68
    //   59: invokeinterface 58 2 0
    //   64: checkcast 62	java/lang/String
    //   67: invokevirtual 70	java/lang/String:equals	(Ljava/lang/Object;)Z
    //   70: ifeq +32 -> 102
    //   73: new 73	com/rongdu/cashloan/cl/model/tongdun/util/DecryptUtil
    //   76: dup
    //   77: ldc 75
    //   79: invokespecial 77	com/rongdu/cashloan/cl/model/tongdun/util/DecryptUtil:<init>	(Ljava/lang/String;)V
    //   82: astore 9
    //   84: aload 9
    //   86: aload_3
    //   87: ldc 56
    //   89: invokeinterface 58 2 0
    //   94: checkcast 62	java/lang/String
    //   97: invokevirtual 80	com/rongdu/cashloan/cl/model/tongdun/util/DecryptUtil:decrypt	(Ljava/lang/String;)Ljava/lang/String;
    //   100: astore 4
    //   102: aload 4
    //   104: invokestatic 84	com/rongdu/cashloan/core/common/util/StringUtil:isEmpty	(Ljava/lang/CharSequence;)Z
    //   107: ifne +11 -> 118
    //   110: aload 4
    //   112: invokestatic 89	com/rongdu/cashloan/core/common/util/StringUtil:isPhone	(Ljava/lang/String;)Z
    //   115: ifne +95 -> 210
    //   118: aload 8
    //   120: ldc 93
    //   122: aload 7
    //   124: invokeinterface 95 3 0
    //   129: pop
    //   130: aload 8
    //   132: ldc 99
    //   134: ldc 101
    //   136: invokeinterface 95 3 0
    //   141: pop
    //   142: aload 8
    //   144: ldc 56
    //   146: aload 4
    //   148: invokeinterface 95 3 0
    //   153: pop
    //   154: aload_0
    //   155: getfield 103	com/rongdu/cashloan/manage/controller/ChannelThridRegisterController:response	Ljavax/servlet/http/HttpServletResponse;
    //   158: aload 8
    //   160: invokestatic 107	com/rongdu/cashloan/core/common/util/ServletUtils:writeToResponse	(Ljavax/servlet/http/HttpServletResponse;Ljava/util/Map;)V
    //   163: new 113	com/rongdu/cashloan/cl/domain/ChannelThirdLog
    //   166: dup
    //   167: lload 5
    //   169: invokestatic 115	java/lang/Long:valueOf	(J)Ljava/lang/Long;
    //   172: aload 4
    //   174: aload 7
    //   176: invokestatic 121	java/lang/Integer:valueOf	(Ljava/lang/String;)Ljava/lang/Integer;
    //   179: aload_2
    //   180: aload 8
    //   182: invokestatic 126	com/alibaba/fastjson/JSONObject:toJSONString	(Ljava/lang/Object;)Ljava/lang/String;
    //   185: new 132	java/util/Date
    //   188: dup
    //   189: invokespecial 134	java/util/Date:<init>	()V
    //   192: invokespecial 135	com/rongdu/cashloan/cl/domain/ChannelThirdLog:<init>	(Ljava/lang/Long;Ljava/lang/String;Ljava/lang/Integer;Ljava/lang/String;Ljava/lang/String;Ljava/util/Date;)V
    //   195: astore 12
    //   197: aload_0
    //   198: getfield 138	com/rongdu/cashloan/manage/controller/ChannelThridRegisterController:channelThirdLogService	Lcom/rongdu/cashloan/cl/service/ChannelThirdLogService;
    //   201: aload 12
    //   203: invokeinterface 140 2 0
    //   208: pop
    //   209: return
    //   210: aload_0
    //   211: getfield 146	com/rongdu/cashloan/manage/controller/ChannelThridRegisterController:clSmsService	Lcom/rongdu/cashloan/cl/service/ClSmsService;
    //   214: aload 4
    //   216: invokeinterface 148 2 0
    //   221: ifle +95 -> 316
    //   224: aload 8
    //   226: ldc 93
    //   228: aload 7
    //   230: invokeinterface 95 3 0
    //   235: pop
    //   236: aload 8
    //   238: ldc 99
    //   240: ldc 101
    //   242: invokeinterface 95 3 0
    //   247: pop
    //   248: aload 8
    //   250: ldc 56
    //   252: aload 4
    //   254: invokeinterface 95 3 0
    //   259: pop
    //   260: aload_0
    //   261: getfield 103	com/rongdu/cashloan/manage/controller/ChannelThridRegisterController:response	Ljavax/servlet/http/HttpServletResponse;
    //   264: aload 8
    //   266: invokestatic 107	com/rongdu/cashloan/core/common/util/ServletUtils:writeToResponse	(Ljavax/servlet/http/HttpServletResponse;Ljava/util/Map;)V
    //   269: new 113	com/rongdu/cashloan/cl/domain/ChannelThirdLog
    //   272: dup
    //   273: lload 5
    //   275: invokestatic 115	java/lang/Long:valueOf	(J)Ljava/lang/Long;
    //   278: aload 4
    //   280: aload 7
    //   282: invokestatic 121	java/lang/Integer:valueOf	(Ljava/lang/String;)Ljava/lang/Integer;
    //   285: aload_2
    //   286: aload 8
    //   288: invokestatic 126	com/alibaba/fastjson/JSONObject:toJSONString	(Ljava/lang/Object;)Ljava/lang/String;
    //   291: new 132	java/util/Date
    //   294: dup
    //   295: invokespecial 134	java/util/Date:<init>	()V
    //   298: invokespecial 135	com/rongdu/cashloan/cl/domain/ChannelThirdLog:<init>	(Ljava/lang/Long;Ljava/lang/String;Ljava/lang/Integer;Ljava/lang/String;Ljava/lang/String;Ljava/util/Date;)V
    //   301: astore 12
    //   303: aload_0
    //   304: getfield 138	com/rongdu/cashloan/manage/controller/ChannelThridRegisterController:channelThirdLogService	Lcom/rongdu/cashloan/cl/service/ChannelThirdLogService;
    //   307: aload 12
    //   309: invokeinterface 140 2 0
    //   314: pop
    //   315: return
    //   316: aload_3
    //   317: ldc -102
    //   319: invokeinterface 58 2 0
    //   324: checkcast 62	java/lang/String
    //   327: invokestatic 156	com/rongdu/cashloan/core/common/util/StringUtil:isNotBlank	(Ljava/lang/CharSequence;)Z
    //   330: ifeq +100 -> 430
    //   333: ldc -97
    //   335: invokestatic 161	tool/util/BeanUtil:getBean	(Ljava/lang/String;)Ljava/lang/Object;
    //   338: checkcast 167	com/rongdu/cashloan/cl/service/ChannelService
    //   341: astore 9
    //   343: aload 9
    //   345: aload_3
    //   346: ldc -102
    //   348: invokeinterface 58 2 0
    //   353: checkcast 62	java/lang/String
    //   356: invokeinterface 169 2 0
    //   361: astore 10
    //   363: aload 10
    //   365: ifnull +13 -> 378
    //   368: aload 10
    //   370: invokevirtual 173	com/rongdu/cashloan/cl/domain/Channel:getId	()Ljava/lang/Long;
    //   373: invokevirtual 179	java/lang/Long:longValue	()J
    //   376: lstore 5
    //   378: aload_0
    //   379: getfield 183	com/rongdu/cashloan/manage/controller/ChannelThridRegisterController:userService	Lcom/rongdu/cashloan/manage/service/UserService;
    //   382: aload_1
    //   383: aload 4
    //   385: lload 5
    //   387: invokevirtual 185	com/rongdu/cashloan/manage/service/UserService:registerUser	(Ljavax/servlet/http/HttpServletRequest;Ljava/lang/String;J)V
    //   390: ldc -65
    //   392: astore 7
    //   394: aload 8
    //   396: ldc -63
    //   398: aload 7
    //   400: invokeinterface 95 3 0
    //   405: pop
    //   406: aload 8
    //   408: ldc 99
    //   410: ldc -61
    //   412: invokeinterface 95 3 0
    //   417: pop
    //   418: aload 8
    //   420: ldc 56
    //   422: aload 4
    //   424: invokeinterface 95 3 0
    //   429: pop
    //   430: aload_0
    //   431: getfield 103	com/rongdu/cashloan/manage/controller/ChannelThridRegisterController:response	Ljavax/servlet/http/HttpServletResponse;
    //   434: aload 8
    //   436: invokestatic 107	com/rongdu/cashloan/core/common/util/ServletUtils:writeToResponse	(Ljavax/servlet/http/HttpServletResponse;Ljava/util/Map;)V
    //   439: goto +110 -> 549
    //   442: astore 9
    //   444: aload 9
    //   446: invokevirtual 197	java/lang/Exception:printStackTrace	()V
    //   449: new 113	com/rongdu/cashloan/cl/domain/ChannelThirdLog
    //   452: dup
    //   453: lload 5
    //   455: invokestatic 115	java/lang/Long:valueOf	(J)Ljava/lang/Long;
    //   458: aload 4
    //   460: aload 7
    //   462: invokestatic 121	java/lang/Integer:valueOf	(Ljava/lang/String;)Ljava/lang/Integer;
    //   465: aload_2
    //   466: aload 8
    //   468: invokestatic 126	com/alibaba/fastjson/JSONObject:toJSONString	(Ljava/lang/Object;)Ljava/lang/String;
    //   471: new 132	java/util/Date
    //   474: dup
    //   475: invokespecial 134	java/util/Date:<init>	()V
    //   478: invokespecial 135	com/rongdu/cashloan/cl/domain/ChannelThirdLog:<init>	(Ljava/lang/Long;Ljava/lang/String;Ljava/lang/Integer;Ljava/lang/String;Ljava/lang/String;Ljava/util/Date;)V
    //   481: astore 12
    //   483: aload_0
    //   484: getfield 138	com/rongdu/cashloan/manage/controller/ChannelThridRegisterController:channelThirdLogService	Lcom/rongdu/cashloan/cl/service/ChannelThirdLogService;
    //   487: aload 12
    //   489: invokeinterface 140 2 0
    //   494: pop
    //   495: goto +100 -> 595
    //   498: astore 11
    //   500: new 113	com/rongdu/cashloan/cl/domain/ChannelThirdLog
    //   503: dup
    //   504: lload 5
    //   506: invokestatic 115	java/lang/Long:valueOf	(J)Ljava/lang/Long;
    //   509: aload 4
    //   511: aload 7
    //   513: invokestatic 121	java/lang/Integer:valueOf	(Ljava/lang/String;)Ljava/lang/Integer;
    //   516: aload_2
    //   517: aload 8
    //   519: invokestatic 126	com/alibaba/fastjson/JSONObject:toJSONString	(Ljava/lang/Object;)Ljava/lang/String;
    //   522: new 132	java/util/Date
    //   525: dup
    //   526: invokespecial 134	java/util/Date:<init>	()V
    //   529: invokespecial 135	com/rongdu/cashloan/cl/domain/ChannelThirdLog:<init>	(Ljava/lang/Long;Ljava/lang/String;Ljava/lang/Integer;Ljava/lang/String;Ljava/lang/String;Ljava/util/Date;)V
    //   532: astore 12
    //   534: aload_0
    //   535: getfield 138	com/rongdu/cashloan/manage/controller/ChannelThridRegisterController:channelThirdLogService	Lcom/rongdu/cashloan/cl/service/ChannelThirdLogService;
    //   538: aload 12
    //   540: invokeinterface 140 2 0
    //   545: pop
    //   546: aload 11
    //   548: athrow
    //   549: new 113	com/rongdu/cashloan/cl/domain/ChannelThirdLog
    //   552: dup
    //   553: lload 5
    //   555: invokestatic 115	java/lang/Long:valueOf	(J)Ljava/lang/Long;
    //   558: aload 4
    //   560: aload 7
    //   562: invokestatic 121	java/lang/Integer:valueOf	(Ljava/lang/String;)Ljava/lang/Integer;
    //   565: aload_2
    //   566: aload 8
    //   568: invokestatic 126	com/alibaba/fastjson/JSONObject:toJSONString	(Ljava/lang/Object;)Ljava/lang/String;
    //   571: new 132	java/util/Date
    //   574: dup
    //   575: invokespecial 134	java/util/Date:<init>	()V
    //   578: invokespecial 135	com/rongdu/cashloan/cl/domain/ChannelThirdLog:<init>	(Ljava/lang/Long;Ljava/lang/String;Ljava/lang/Integer;Ljava/lang/String;Ljava/lang/String;Ljava/util/Date;)V
    //   581: astore 12
    //   583: aload_0
    //   584: getfield 138	com/rongdu/cashloan/manage/controller/ChannelThridRegisterController:channelThirdLogService	Lcom/rongdu/cashloan/cl/service/ChannelThirdLogService;
    //   587: aload 12
    //   589: invokeinterface 140 2 0
    //   594: pop
    //   595: return
    // Line number table:
    //   Java source line #72	-> byte code offset #0
    //   Java source line #73	-> byte code offset #8
    //   Java source line #74	-> byte code offset #15
    //   Java source line #78	-> byte code offset #25
    //   Java source line #81	-> byte code offset #38
    //   Java source line #83	-> byte code offset #41
    //   Java source line #84	-> byte code offset #45
    //   Java source line #88	-> byte code offset #54
    //   Java source line #90	-> byte code offset #73
    //   Java source line #91	-> byte code offset #84
    //   Java source line #93	-> byte code offset #102
    //   Java source line #94	-> byte code offset #118
    //   Java source line #95	-> byte code offset #130
    //   Java source line #96	-> byte code offset #142
    //   Java source line #97	-> byte code offset #154
    //   Java source line #147	-> byte code offset #163
    //   Java source line #148	-> byte code offset #197
    //   Java source line #98	-> byte code offset #209
    //   Java source line #101	-> byte code offset #210
    //   Java source line #102	-> byte code offset #224
    //   Java source line #103	-> byte code offset #236
    //   Java source line #104	-> byte code offset #248
    //   Java source line #105	-> byte code offset #260
    //   Java source line #147	-> byte code offset #269
    //   Java source line #148	-> byte code offset #303
    //   Java source line #106	-> byte code offset #315
    //   Java source line #128	-> byte code offset #316
    //   Java source line #129	-> byte code offset #333
    //   Java source line #130	-> byte code offset #343
    //   Java source line #131	-> byte code offset #363
    //   Java source line #132	-> byte code offset #368
    //   Java source line #136	-> byte code offset #378
    //   Java source line #137	-> byte code offset #390
    //   Java source line #138	-> byte code offset #394
    //   Java source line #139	-> byte code offset #406
    //   Java source line #140	-> byte code offset #418
    //   Java source line #142	-> byte code offset #430
    //   Java source line #143	-> byte code offset #439
    //   Java source line #144	-> byte code offset #444
    //   Java source line #147	-> byte code offset #449
    //   Java source line #148	-> byte code offset #483
    //   Java source line #145	-> byte code offset #498
    //   Java source line #147	-> byte code offset #500
    //   Java source line #148	-> byte code offset #534
    //   Java source line #149	-> byte code offset #546
    //   Java source line #147	-> byte code offset #549
    //   Java source line #148	-> byte code offset #583
    //   Java source line #150	-> byte code offset #595
    // Local variable table:
    //   start	length	slot	name	signature
    //   0	596	0	this	ChannelThridRegisterController
    //   0	596	1	request	javax.servlet.http.HttpServletRequest
    //   0	596	2	data	String
    //   7	339	3	searchMap	java.util.Map<String, Object>
    //   36	523	4	phone	String
    //   39	515	5	channelId	long
    //   43	518	7	status	String
    //   52	515	8	ret	java.util.Map<String, Object>
    //   82	3	9	des	com.rongdu.cashloan.cl.model.tongdun.util.DecryptUtil
    //   341	3	9	channelService	com.rongdu.cashloan.cl.service.ChannelService
    //   442	3	9	e	Exception
    //   361	8	10	channel	com.rongdu.cashloan.cl.domain.Channel
    //   498	49	11	localObject	Object
    //   195	7	12	channelThirdLog	com.rongdu.cashloan.cl.domain.ChannelThirdLog
    //   301	7	12	channelThirdLog	com.rongdu.cashloan.cl.domain.ChannelThirdLog
    //   481	7	12	channelThirdLog	com.rongdu.cashloan.cl.domain.ChannelThirdLog
    //   532	7	12	channelThirdLog	com.rongdu.cashloan.cl.domain.ChannelThirdLog
    //   581	7	12	channelThirdLog	com.rongdu.cashloan.cl.domain.ChannelThirdLog
    // Exception table:
    //   from	to	target	type
    //   54	163	442	java/lang/Exception
    //   210	269	442	java/lang/Exception
    //   316	439	442	java/lang/Exception
    //   54	163	498	finally
    //   210	269	498	finally
    //   316	449	498	finally
  }
}


/* Location:              D:\workspace\小贷平台运行包\manage\WEB-INF\classes\!\com\rongdu\cashloan\manage\controller\ChannelThridRegisterController.class
 * Java compiler version: 7 (51.0)
 * JD-Core Version:       0.7.1
 */